endstone_qqsync_webui_plugin/__init__.py
endstone_qqsync_webui_plugin/api.py
endstone_qqsync_webui_plugin/config.py
endstone_qqsync_webui_plugin/qqsync_webui_plugin.py
endstone_qqsync_webui_plugin/server.py
endstone_qqsync_webui_plugin/lib/typing_extensions.py
endstone_qqsync_webui_plugin/lib/aiohappyeyeballs/__init__.py
endstone_qqsync_webui_plugin/lib/aiohappyeyeballs/_staggered.py
endstone_qqsync_webui_plugin/lib/aiohappyeyeballs/impl.py
endstone_qqsync_webui_plugin/lib/aiohappyeyeballs/py.typed
endstone_qqsync_webui_plugin/lib/aiohappyeyeballs/types.py
endstone_qqsync_webui_plugin/lib/aiohappyeyeballs/utils.py
endstone_qqsync_webui_plugin/lib/aiohttp/__init__.py
endstone_qqsync_webui_plugin/lib/aiohttp/_cookie_helpers.py
endstone_qqsync_webui_plugin/lib/aiohttp/_cparser.pxd
endstone_qqsync_webui_plugin/lib/aiohttp/_find_header.pxd
endstone_qqsync_webui_plugin/lib/aiohttp/_headers.pxi
endstone_qqsync_webui_plugin/lib/aiohttp/_http_parser.pyx
endstone_qqsync_webui_plugin/lib/aiohttp/_http_writer.pyx
endstone_qqsync_webui_plugin/lib/aiohttp/abc.py
endstone_qqsync_webui_plugin/lib/aiohttp/base_protocol.py
endstone_qqsync_webui_plugin/lib/aiohttp/client.py
endstone_qqsync_webui_plugin/lib/aiohttp/client_exceptions.py
endstone_qqsync_webui_plugin/lib/aiohttp/client_middleware_digest_auth.py
endstone_qqsync_webui_plugin/lib/aiohttp/client_middlewares.py
endstone_qqsync_webui_plugin/lib/aiohttp/client_proto.py
endstone_qqsync_webui_plugin/lib/aiohttp/client_reqrep.py
endstone_qqsync_webui_plugin/lib/aiohttp/client_ws.py
endstone_qqsync_webui_plugin/lib/aiohttp/compression_utils.py
endstone_qqsync_webui_plugin/lib/aiohttp/connector.py
endstone_qqsync_webui_plugin/lib/aiohttp/cookiejar.py
endstone_qqsync_webui_plugin/lib/aiohttp/formdata.py
endstone_qqsync_webui_plugin/lib/aiohttp/hdrs.py
endstone_qqsync_webui_plugin/lib/aiohttp/helpers.py
endstone_qqsync_webui_plugin/lib/aiohttp/http.py
endstone_qqsync_webui_plugin/lib/aiohttp/http_exceptions.py
endstone_qqsync_webui_plugin-0.0.1.dist-info/METADATA
endstone_qqsync_webui_plugin-0.0.1.dist-info/WHEEL
endstone_qqsync_webui_plugin-0.0.1.dist-info/entry_points.txt
endstone_qqsync_webui_plugin-0.0.1.dist-info/RECORD
