Metadata-Version: 2.4
Name: endstone-qqsync-webui-plugin
Version: 0.0.1
Summary: QQsync WebUI 拓展
Project-URL: Homepage, https://github.com/yuexps/endstone-qqsync-webui-plugin
Author-email: yuexps <yuexps@qq.com>
Requires-Python: >=3.11
